Workbook

Sheet Calculateur
B2: Calculateur de viabilité — POD automatisé (Claude → nanobanana → Printful → Etsy/Amazon)
B3: Modifie uniquement les cellules BLEUES. Tout le reste se recalcule automatiquement.
B5: 1 — ÉCONOMIE D'UNE VENTE
B6: Prix de vente moyen (article) | C6: 25
B7: Port encaissé auprès du client | C7: 5
B8: Base fournisseur + expédition (coût) | C8: 18.5
B9: Frais Etsy — transaction (% du total) | C9: 0.065
B10: Frais Etsy — traitement (% du total) | C10: 0.03
B11: Frais Etsy — traitement (fixe / vente) | C11: 0.25
B12: Frais Etsy — mise en ligne (/ vente) | C12: 0.2
B13: Total encaissé / vente | C13: =C6+C7 -> 30
B14: Total frais Etsy / vente | C14: =C13*(C9+C10)+C11+C12 -> 3.3
B15: MARGE NETTE / VENTE | C15: =C13-C14-C8 -> 8.2
B17: 2 — PARAMÈTRES DU CATALOGUE
B18: Designs produits / mois | C18: 1000
B19: Coût chargé / design listé | C19: 0.5
B20: Hit-rate (% designs qui vendent) | C20: 0.05
B21: Ventes moy. / design gagnant / mois | C21: 3
B22: Frais fixes mensuels (outils, abos) | C22: 150
B24: 3 — RÉSULTAT MENSUEL (selon hit-rate ci-dessus)
B25: Designs gagnants / mois | C25: =C18*C20 -> 50
B26: Ventes / mois | C26: =C25*C21 -> 150
B27: Revenu net des ventes | C27: =C26*C15 -> 1230
B28: Coût de production (tous designs) | C28: =-C18*C19 -> -500
B29: Frais fixes | C29: =-C22 -> -150
B30: RÉSULTAT MENSUEL | C30: =C27+C28+C29 -> 580
B31: HIT-RATE DE RENTABILITÉ (seuil) | C31: =(C18*C19+C22)/(C18*C21*C15) -> 0.026422764
B32: Marge sur seuil (hit-rate actuel − seuil) | C32: =C20-C31 -> 0.023577236
B34: 4 — SENSIBILITÉ AU HIT-RATE (le facteur qui décide de tout)
B35: Hit-rate | C35: 0.01 | D35: 0.02 | E35: 0.03 | F35: 0.04 | G35: 0.05 | H35: 0.06 | I35: 0.08 | J35: 0.1
B36: Résultat mensuel | C36: =(C18*0.01*C21*C15)-(C18*C19)-C22 -> -404 | D36: =(C18*0.02*C21*C15)-(C18*C19)-C22 -> -158 | E36: =(C18*0.03*C21*C15)-(C18*C19)-C22 -> 88 | F36: =(C18*0.04*C21*C15)-(C18*C19)-C22 -> 334 | G36: =(C18*0.05*C21*C15)-(C18*C19)-C22 -> 580 | H36: =(C18*0.06*C21*C15)-(C18*C19)-C22 -> 826 | I36: =(C18*0.08*C21*C15)-(C18*C19)-C22 -> 1318 | J36: =(C18*0.1*C21*C15)-(C18*C19)-C22 -> 1810
B37: Résultat annuel | C37: =C36*12 -> -4848 | D37: =D36*12 -> -1896 | E37: =E36*12 -> 1056 | F37: =F36*12 -> 4008 | G37: =G36*12 -> 6960 | H37: =H36*12 -> 9912 | I37: =I36*12 -> 15816 | J37: =J36*12 -> 21720
B39: Lecture
B40: • Le seuil de rentabilité (cellule jaune §3) est calculé automatiquement à partir de TES chiffres.
B41: • Sous ce seuil, produire plus de designs = perdre plus d'argent (coûts des SKU morts).
B42: • Doubler le hit-rate vaut bien mieux que doubler le volume : c'est le job du moteur de scoring.
B43: • ⚠ Au-delà de 10 000 $/an de ventes, Etsy impose les Offsite Ads (15 %) : ajoute ~3-5 pts de frais.
B44: • Je ne suis ni conseiller juridique ni financier — le volet PI mérite un avis spécialisé avant de scaler.

Sheet Comparateur fournisseurs
B2: Comparateur de fournisseurs — effet sur la marge et le seuil de rentabilité
B3: Coûts de base INDICATIFS (poster, à confirmer sur les sites). Modifie les cellules bleues. Hypothèses liées au Calculateur.
B5: Hypothèses communes (liées au Calculateur)
B6: Total encaissé / vente | C6: =Calculateur!C13 -> 30
B7: Total frais Etsy / vente | C7: =Calculateur!C14 -> 3.3
B8: Designs produits / mois | C8: =Calculateur!C18 -> 1000
B9: Coût chargé / design | C9: =Calculateur!C19 -> 0.5
B10: Ventes / gagnant / mois | C10: =Calculateur!C21 -> 3
B11: Frais fixes mensuels | C11: =Calculateur!C22 -> 150
B12: Hit-rate actuel | C12: =Calculateur!C20 -> 0.05
B13: Fournisseur | C13: Base + envoi ($) | D13: Marge nette/vente | E13: Seuil hit-rate | F13: Résultat mensuel @ hit-rate actuel | G13: Baisse du seuil vs Printful
B14: Printful (référence) | C14: 18.5 | D14: =$C$6-$C$7-C14 -> 8.2 | E14: =($C$8*$C$9+$C$11)/($C$8*$C$10*D14) -> 0.026422764 | F14: =($C$8*$C$12*$C$10*D14)-($C$8*$C$9)-$C$11 -> 580 | G14: =$E$14-E14 -> 0
B15: Gelato giclée (UE) | C15: 16 | D15: =$C$6-$C$7-C15 -> 10.7 | E15: =($C$8*$C$9+$C$11)/($C$8*$C$10*D15) -> 0.020249221 | F15: =($C$8*$C$12*$C$10*D15)-($C$8*$C$9)-$C$11 -> 955 | G15: =$E$14-E15 -> 0.006173543
B16: Prodigi premium (UE) | C16: 15 | D16: =$C$6-$C$7-C16 -> 11.7 | E16: =($C$8*$C$9+$C$11)/($C$8*$C$10*D16) -> 0.018518519 | F16: =($C$8*$C$12*$C$10*D16)-($C$8*$C$9)-$C$11 -> 1105 | G16: =$E$14-E16 -> 0.0079042457
B17: Printify (le moins cher) | C17: 13 | D17: =$C$6-$C$7-C17 -> 13.7 | E17: =($C$8*$C$9+$C$11)/($C$8*$C$10*D17) -> 0.015815085 | F17: =($C$8*$C$12*$C$10*D17)-($C$8*$C$9)-$C$11 -> 1405 | G17: =$E$14-E17 -> 0.010607679
B18: Gooten (éco) | C18: 12 | D18: =$C$6-$C$7-C18 -> 14.7 | E18: =($C$8*$C$9+$C$11)/($C$8*$C$10*D18) -> 0.014739229 | F18: =($C$8*$C$12*$C$10*D18)-($C$8*$C$9)-$C$11 -> 1555 | G18: =$E$14-E18 -> 0.011683535
B20: Lecture
B21: • Baisse de la base → marge/vente en hausse → seuil de hit-rate en baisse (le modèle devient plus tolérant).
B22: • Le port compte autant que la base : produire en UE pour des clients UE réduit coût ET délais.
B23: • Ne pas viser le moins cher absolu : ta marque est premium, la qualité d'impression soutient le prix.
B24: • Coûts INDICATIFS : remplace par les prix réels du produit/format que tu vends.
